rheia/__init__.py
rheia/CASES/__init__.py
rheia/CASES/determine_stoch_des_space.py
rheia/CASES/DATA/climate/climate_Brussels.CSV
rheia/CASES/DATA/climate/climate_Madrid.CSV
rheia/CASES/DATA/climate/climate_Paris.CSV
rheia/CASES/DATA/demand/load_Brussels_dwelling.csv
rheia/CASES/DATA/demand/load_Madrid_dwelling.csv
rheia/CASES/DATA/demand/load_Paris_dwelling.csv
rheia/CASES/ENERGYPLAN/__init__.py
rheia/CASES/ENERGYPLAN/case.txt
rheia/CASES/ENERGYPLAN/case_description.py
rheia/CASES/ENERGYPLAN/design_space.csv
rheia/CASES/ENERGYPLAN/run_energyplan.py
rheia/CASES/ENERGYPLAN/stochastic_space.csv
rheia/CASES/ENERGYPLAN/__pycache__/__init__.cpython-311.pyc
rheia/CASES/ENERGYPLAN/__pycache__/case_description.cpython-311.pyc
rheia/CASES/ENERGYPLAN/__pycache__/run_energyplan.cpython-311.pyc
rheia/CASES/ENERGYSCOPE/2023-10-24_15-23-43.040013.energyscope.log
rheia/CASES/ENERGYSCOPE/__init__.py
rheia/CASES/ENERGYSCOPE/case_description.py
rheia/CASES/ENERGYSCOPE/config_ref_UQ.yaml
rheia/CASES/ENERGYSCOPE/design_space.csv
rheia/CASES/ENERGYSCOPE/design_space_ref.csv
rheia/CASES/ENERGYSCOPE/stochastic_space.csv
rheia/CASES/ENERGYSCOPE/stochastic_space_ref.csv
rheia/CASES/ENERGYSCOPE/uq_estd.py
rheia/CASES/ENERGYSCOPE/__pycache__/__init__.cpython-311.pyc
rheia/CASES/ENERGYSCOPE/__pycache__/case_description.cpython-311.pyc
rheia/CASES/ENERGYSCOPE/__pycache__/uq_estd.cpython-311.pyc
rheia/CASES/FOUR_BAR_TRUSS/__init__.py
rheia/CASES/FOUR_BAR_TRUSS/case_description.py
rheia/CASES/FOUR_BAR_TRUSS/design_space.csv
rheia/CASES/FOUR_BAR_TRUSS/four_bar_truss.py
rheia/CASES/FOUR_BAR_TRUSS/stochastic_space.csv
rheia/CASES/FOUR_BAR_TRUSS/__pycache__/__init__.cpython-311.pyc
rheia/CASES/FOUR_BAR_TRUSS/__pycache__/case_description.cpython-311.pyc
rheia/CASES/FOUR_BAR_TRUSS/__pycache__/four_bar_truss.cpython-311.pyc
rheia/CASES/H2_FUEL/__init__.py
rheia/CASES/H2_FUEL/case_description.py
rheia/CASES/H2_FUEL/design_space.csv
rheia/CASES/H2_FUEL/design_space_tutorial_0.csv
rheia_meca2675-1.1.15.dist-info/licenses/LICENSE
rheia_meca2675-1.1.15.dist-info/METADATA
rheia_meca2675-1.1.15.dist-info/WHEEL
rheia_meca2675-1.1.15.dist-info/top_level.txt
rheia_meca2675-1.1.15.dist-info/RECORD
