Metadata-Version: 2.4
Name: rheia_meca2675
Version: 1.1.15
Summary: Robust design optimization of renewable Hydrogen and dErIved energy cArrier systems
Home-page: https://github.com/rheia-framework/RHEIA
Author: Diederik Coppitters, Panagiotis Tsirikoglou, Ward De Paepe, Konstantinos Kyprianidis, Anestis Kalfas, Francesco Contino
Author-email: rheia.framework@gmail.com
Classifier: Programming Language :: Python :: 3
Classifier: License :: OSI Approved :: MIT License
Classifier: Operating System :: OS Independent
Requires-Python: >=3.9
License-File: LICENSE
Requires-Dist: pyDOE>=0.3.8
Requires-Dist: deap>=1.3.1
Requires-Dist: numpy>=1.24.1
Requires-Dist: scipy>=1.10.0
Requires-Dist: sobolsequence>=0.2.1
Requires-Dist: pandas>=1.5.3
Requires-Dist: matplotlib>=3.2.2
Requires-Dist: pvlib>=0.9.4
Requires-Dist: h5py>=3.8.0
Dynamic: author
Dynamic: author-email
Dynamic: classifier
Dynamic: home-page
Dynamic: license-file
Dynamic: requires-dist
Dynamic: requires-python
Dynamic: summary
